{
  "node" : "routing.node",
  "transport" : [ {
    "api" : { },
    "type" : "UDP",
    "port" : 8009,
    "timeout" : 2000,
    "maxRequestBytes" : 512
  }, {
    "api" : { },
    "type" : "TCP",
    "port" : 8010,
    "timeout" : 2000,
    "maxRequestBytes" : 512
  }, {
    "api" : { },
    "type" : "WEBSOCKET",
    "port" : 8020,
    "timeout" : 4000,
    "maxRequestBytes" : 512
  }, {
    "api" : {
      "/api/realmlist" : {
        "target" : "client.realmregistry.node",
        "route" : "realmlist"
      },
      "/api/news" : {
        "target" : "patching.node",
        "route" : "news"
      },
      "/api/gameinfo" : {
        "target" : "patching.node",
        "route" : "gameinfo"
      }
    },
    "type" : "REST",
    "port" : 1443,
    "timeout" : 3000,
    "maxRequestBytes" : 512,
    "defaultTarget" : "webserver.node"
  } ],
  "external" : {
    "client.authentication.node" : ".*",
    "client.realmregistry.node" : ".*",
    "patching.node" : ".*"
  },
  "global" : "VVuCMk0jeITAJ5HIa5GUfX1cO+wLThDyyaQiL6OXU6MdYWbThampCsOnnonTDRKwxQuFwerpwXET5WV9vi65uA==",
  "logging" : {
    "properties" : { },
    "key" : "oui9FmWdB4tYzGD3DzsYcjiCxrYwTqB8Uwl9QIZx/NdvlEi4+XnpDt9WFhBc8mq+ONqSMbvzhBop317PGbrURw==",
    "domain" : "routing.node",
    "expiry" : 1523722968
  }
}